test_run_dir/Instruction_Aligner_Test/InstAligner.v
module InstAligner(
  input         clock,
  input         reset,
  input  [31:0] io_instIn,
  output [31:0] io_instOut,
  input  [31:0] io_pcIn,
  output [31:0] io_pcOut
);
`ifdef RANDOMIZE_REG_INIT
  reg [31:0] _RAND_0;
  reg [31:0] _RAND_1;
  reg [31:0] _RAND_2;
  reg [31:0] _RAND_3;
  reg [31:0] _RAND_4;
  reg [31:0] _RAND_5;
  reg [31:0] _RAND_6;
`endif // RANDOMIZE_REG_INIT
  reg  case1; // @[InstAligner.scala 16:24]
  reg  case2; // @[InstAligner.scala 17:24]
  reg [31:0] instReg; // @[InstAligner.scala 18:26]
  wire  _T = ~case1; // @[Conditional.scala 37:30]
  wire  _T_2 = io_instIn[1:0] != 2'h3; // @[InstAligner.scala 27:33]
  wire  _T_4 = io_instIn[17:16] != 2'h3; // @[InstAligner.scala 27:61]
  reg [15:0] io_instOut_REG; // @[InstAligner.scala 28:38]
  reg [31:0] instReg_REG; // @[InstAligner.scala 30:35]
  wire [31:0] _io_pcOut_T_1 = io_pcIn + 32'h2; // @[InstAligner.scala 31:53]
  reg [31:0] io_pcOut_REG; // @[InstAligner.scala 31:44]
  reg [31:0] io_pcOut_REG_1; // @[InstAligner.scala 31:36]
  wire [31:0] _GEN_0 = io_instIn[1:0] != 2'h3 & io_instIn[17:16] != 2'h3 ? {{16'd0}, io_instOut_REG} : instReg; // @[InstAligner.scala 27:69 InstAligner.scala 28:28 InstAligner.scala 20:16]
  wire [31:0] _GEN_1 = io_instIn[1:0] != 2'h3 & io_instIn[17:16] != 2'h3 ? instReg_REG : instReg; // @[InstAligner.scala 27:69 InstAligner.scala 30:25 InstAligner.scala 18:26]
  wire [31:0] _GEN_2 = io_instIn[1:0] != 2'h3 & io_instIn[17:16] != 2'h3 ? io_pcOut_REG_1 : io_pcIn; // @[InstAligner.scala 27:69 InstAligner.scala 31:26 InstAligner.scala 19:14]
  wire  _GEN_3 = io_instIn[1:0] != 2'h3 & io_instIn[17:16] != 2'h3 | case1; // @[InstAligner.scala 27:69 InstAligner.scala 32:23 InstAligner.scala 16:24]
  wire [31:0] _GEN_4 = case1 ? {{16'd0}, instReg[31:16]} : instReg; // @[Conditional.scala 39:67 InstAligner.scala 36:24 InstAligner.scala 20:16]
  wire [31:0] _GEN_5 = case1 ? _io_pcOut_T_1 : io_pcIn; // @[Conditional.scala 39:67 InstAligner.scala 38:22 InstAligner.scala 19:14]
  wire  _GEN_6 = case1 ? 1'h0 : case1; // @[Conditional.scala 39:67 InstAligner.scala 39:19 InstAligner.scala 16:24]
  wire [31:0] _GEN_7 = _T ? _GEN_0 : _GEN_4; // @[Conditional.scala 40:58]
  wire [31:0] _GEN_8 = _T ? _GEN_1 : instReg; // @[Conditional.scala 40:58 InstAligner.scala 18:26]
  wire [31:0] _GEN_9 = _T ? _GEN_2 : _GEN_5; // @[Conditional.scala 40:58]
  wire  _GEN_10 = _T ? _GEN_3 : _GEN_6; // @[Conditional.scala 40:58]
  wire  _T_7 = ~case2; // @[Conditional.scala 37:30]
  wire  _T_11 = io_instIn[17:16] == 2'h3; // @[InstAligner.scala 46:61]
  wire [31:0] _GEN_11 = _T_2 & io_instIn[17:16] == 2'h3 ? {{16'd0}, io_instIn[15:0]} : _GEN_7; // @[InstAligner.scala 46:69 InstAligner.scala 47:28]
  wire [31:0] _GEN_13 = _T_2 & io_instIn[17:16] == 2'h3 ? _io_pcOut_T_1 : _GEN_9; // @[InstAligner.scala 46:69 InstAligner.scala 50:26]
  wire  _GEN_14 = _T_2 & io_instIn[17:16] == 2'h3 | case2; // @[InstAligner.scala 46:69 InstAligner.scala 51:23 InstAligner.scala 17:24]
  wire [31:0] _io_instOut_T_3 = {io_instIn[15:0],instReg[31:16]}; // @[Cat.scala 30:58]
  wire [31:0] _io_pcOut_T_7 = io_pcIn + 32'h4; // @[InstAligner.scala 57:33]
  wire [31:0] _GEN_15 = _T_11 ? io_instIn : _GEN_8; // @[InstAligner.scala 61:49 InstAligner.scala 62:25]
  wire [31:0] _GEN_20 = case2 ? _io_instOut_T_3 : _GEN_7; // @[Conditional.scala 39:67 InstAligner.scala 55:24]
  wire [31:0] _GEN_21 = case2 ? _io_pcOut_T_7 : _GEN_9; // @[Conditional.scala 39:67 InstAligner.scala 57:22]
  assign io_instOut = _T_7 ? _GEN_11 : _GEN_20; // @[Conditional.scala 40:58]
  assign io_pcOut = _T_7 ? _GEN_13 : _GEN_21; // @[Conditional.scala 40:58]
  always @(posedge clock) begin
    if (reset) begin // @[InstAligner.scala 16:24]
      case1 <= 1'h0; // @[InstAligner.scala 16:24]
    end else if (_T_7) begin // @[Conditional.scala 40:58]
      case1 <= _GEN_10;
    end else if (case2) begin // @[Conditional.scala 39:67]
      if (_T_4) begin // @[InstAligner.scala 58:44]
        case1 <= 1'h0; // @[InstAligner.scala 59:23]
      end else begin
        case1 <= _GEN_10;
      end
    end else begin
      case1 <= _GEN_10;
    end
    if (reset) begin // @[InstAligner.scala 17:24]
      case2 <= 1'h0; // @[InstAligner.scala 17:24]
    end else if (_T_7) begin // @[Conditional.scala 40:58]
      case2 <= _GEN_14;
    end else if (case2) begin // @[Conditional.scala 39:67]
      if (_T_4) begin // @[InstAligner.scala 58:44]
        case2 <= 1'h0; // @[InstAligner.scala 60:23]
      end else begin
        case2 <= _T_11;
      end
    end
    if (reset) begin // @[InstAligner.scala 18:26]
      instReg <= io_instIn; // @[InstAligner.scala 18:26]
    end else if (_T_7) begin // @[Conditional.scala 40:58]
      if (_T_2 & io_instIn[17:16] == 2'h3) begin // @[InstAligner.scala 46:69]
        instReg <= io_instIn; // @[InstAligner.scala 49:25]
      end else begin
        instReg <= _GEN_8;
      end
    end else if (case2) begin // @[Conditional.scala 39:67]
      if (_T_4) begin // @[InstAligner.scala 58:44]
        instReg <= _GEN_8;
      end else begin
        instReg <= _GEN_15;
      end
    end else begin
      instReg <= _GEN_8;
    end
    io_instOut_REG <= io_instIn[15:0]; // @[InstAligner.scala 28:48]
    instReg_REG <= io_instIn; // @[InstAligner.scala 30:35]
    io_pcOut_REG <= io_pcIn + 32'h2; // @[InstAligner.scala 31:53]
    io_pcOut_REG_1 <= io_pcOut_REG; // @[InstAligner.scala 31:36]
  end
// Register and memory initialization
`ifdef RANDOMIZE_GARBAGE_ASSIGN
`define RANDOMIZE
`endif
`ifdef RANDOMIZE_INVALID_ASSIGN
`define RANDOMIZE
`endif
`ifdef RANDOMIZE_REG_INIT
`define RANDOMIZE
`endif
`ifdef RANDOMIZE_MEM_INIT
`define RANDOMIZE
`endif
`ifndef RANDOM
`define RANDOM $random
`endif
`ifdef RANDOMIZE_MEM_INIT
  integer initvar;
`endif
`ifndef SYNTHESIS
`ifdef FIRRTL_BEFORE_INITIAL
`FIRRTL_BEFORE_INITIAL
`endif
initial begin
  `ifdef RANDOMIZE
    `ifdef INIT_RANDOM
      `INIT_RANDOM
    `endif
    `ifndef VERILATOR
      `ifdef RANDOMIZE_DELAY
        #`RANDOMIZE_DELAY begin end
      `else
        #0.002 begin end
      `endif
    `endif
`ifdef RANDOMIZE_REG_INIT
  _RAND_0 = {1{`RANDOM}};
  case1 = _RAND_0[0:0];
  _RAND_1 = {1{`RANDOM}};
  case2 = _RAND_1[0:0];
  _RAND_2 = {1{`RANDOM}};
  instReg = _RAND_2[31:0];
  _RAND_3 = {1{`RANDOM}};
  io_instOut_REG = _RAND_3[15:0];
  _RAND_4 = {1{`RANDOM}};
  instReg_REG = _RAND_4[31:0];
  _RAND_5 = {1{`RANDOM}};
  io_pcOut_REG = _RAND_5[31:0];
  _RAND_6 = {1{`RANDOM}};
  io_pcOut_REG_1 = _RAND_6[31:0];
`endif // RANDOMIZE_REG_INIT
  `endif // RANDOMIZE
end // initial
`ifdef FIRRTL_AFTER_INITIAL
`FIRRTL_AFTER_INITIAL
`endif
`endif // SYNTHESIS
endmodule

test_run_dir/Instruction_Aligner_Test/InstAligner.vcd
$version Generated by VerilatedVcd $end
$date Wed Jan 26 14:04:32 2022
 $end
$timescale   1ns $end

 $scope module TOP $end
  $var wire  1 * clock $end
  $var wire 32 , io_instIn [31:0] $end
  $var wire 32 - io_instOut [31:0] $end
  $var wire 32 . io_pcIn [31:0] $end
  $var wire 32 / io_pcOut [31:0] $end
  $var wire  1 + reset $end
  $scope module InstAligner $end
   $var wire  1 # case1 $end
   $var wire  1 $ case2 $end
   $var wire  1 * clock $end
   $var wire 32 % instReg [31:0] $end
   $var wire 32 ' instReg_REG [31:0] $end
   $var wire 32 , io_instIn [31:0] $end
   $var wire 32 - io_instOut [31:0] $end
   $var wire 16 & io_instOut_REG [15:0] $end
   $var wire 32 . io_pcIn [31:0] $end
   $var wire 32 / io_pcOut [31:0] $end
   $var wire 32 ( io_pcOut_REG [31:0] $end
   $var wire 32 ) io_pcOut_REG_1 [31:0] $end
   $var wire  1 + reset $end
  $upscope $end
 $upscope $end
$enddefinitions $end


#0
0#
0$
b00000000000000000000000000000000 %
b0000000000000000 &
b00000000000000000000000000000000 '
b00000000000000000000000000000000 (
b00000000000000000000000000000000 )
0*
1+
b00000000000000000000000000000000 ,
b00000000000000000000000000000000 -
b00000000000000000000000000000000 .
b00000000000000000000000000000000 /
#1
b00000000000000000000000000000010 (
1*
#2
0*
0+
b10010101001011101001010000100110 ,
b00000000000000000000000000001100 .
#3
1#
b1001010000100110 &
b10010101001011101001010000100110 '
b00000000000000000000000000001110 (
b00000000000000000000000000000010 )
1*
b00000000000000000000000000001110 /
#4
0*
b00000000000000000000000000001110 .
b00000000000000000000000000010000 /
#5
0#
b00000000000000000000000000010000 (
b00000000000000000000000000001110 )
1*
b00000000000000001001010000100110 -
b00000000000000000000000000001110 /
#6
0*
#7
1#
b10010101001011101001010000100110 %
b00000000000000000000000000010000 )
1*
b00000000000000001001010100101110 -
b00000000000000000000000000010000 /
#8
0*
b00000000000000000000000000010000 .
b00000000000000000000000000010010 /
#9
0#
b00000000000000000000000000010010 (
1*
b00000000000000001001010000100110 -
b00000000000000000000000000010000 /
#10
0*
#11
1#
b00000000000000000000000000010010 )
1*
b00000000000000001001010100101110 -
b00000000000000000000000000010010 /
#12
0*
b00000000000000000000000000010010 .
b00000000000000000000000000010100 /
#13
0#
b00000000000000000000000000010100 (
1*
b00000000000000001001010000100110 -
b00000000000000000000000000010010 /
#14
0*
#15
1#
b00000000000000000000000000010100 )
1*
b00000000000000001001010100101110 -
b00000000000000000000000000010100 /
#16
0*
#17
0#
1*
b00000000000000001001010000100110 -
#18
0*
#19
1#
1*
b00000000000000001001010100101110 -
#20
0*
#21
0#
1*
b00000000000000001001010000100110 -
#22
0*
#23
1#
1*
b00000000000000001001010100101110 -
#24
0*
#25
0#
1*
b00000000000000001001010000100110 -
#26
0*
#27
1#
1*
b00000000000000001001010100101110 -
#28
0*
#29
0#
1*
b00000000000000001001010000100110 -
#30
0*
#31
1#
1*
b00000000000000001001010100101110 -
#32
0*
#33
0#
1*
b00000000000000001001010000100110 -
#34
0*
#35
1#
1*
b00000000000000001001010100101110 -
#36
0*
#37
0#
1*
b00000000000000001001010000100110 -
#38
0*
#39
1#
1*
b00000000000000001001010100101110 -
#40
0*
#41
0#
1*
b00000000000000001001010000100110 -
#42
0*
#43
1#
1*
b00000000000000001001010100101110 -
#44
0*
#45
0#
1*
b00000000000000001001010000100110 -
#46
0*
#47
1#
1*
b00000000000000001001010100101110 -
#48
0*
#49
0#
1*
b00000000000000001001010000100110 -
#50
0*
#51
1#
1*
b00000000000000001001010100101110 -
#52
0*
#53
0#
1*
b00000000000000001001010000100110 -
#54
0*
#55
1#
1*
b00000000000000001001010100101110 -
#56
0*
#57
0#
1*
b00000000000000001001010000100110 -
#58
0*
#59
1#
1*
b00000000000000001001010100101110 -
#60
0*
#61
0#
1*
b00000000000000001001010000100110 -
#62
0*
#63
1#
1*
b00000000000000001001010100101110 -
#64
0*
#65
0#
1*
b00000000000000001001010000100110 -
#66
0*
#67
1#
1*
b00000000000000001001010100101110 -
#68
0*
#69
0#
1*
b00000000000000001001010000100110 -
#70
0*
#71
1#
1*
b00000000000000001001010100101110 -
#72
0*
#73
0#
1*
b00000000000000001001010000100110 -
#74
0*
#75
1#
1*
b00000000000000001001010100101110 -
#76
0*
#77
0#
1*
b00000000000000001001010000100110 -
#78
0*
#79
1#
1*
b00000000000000001001010100101110 -
#80
0*
#81
0#
1*
b00000000000000001001010000100110 -
#82
0*
#83
1#
1*
b00000000000000001001010100101110 -
#84
0*
#85
0#
1*
b00000000000000001001010000100110 -
#86
0*
#87
1#
1*
b00000000000000001001010100101110 -
#88
0*
#89
0#
1*
b00000000000000001001010000100110 -
#90
0*
#91
1#
1*
b00000000000000001001010100101110 -
#92
0*
#93
0#
1*
b00000000000000001001010000100110 -
#94
0*
#95
1#
1*
b00000000000000001001010100101110 -
#96
0*
#97
0#
1*
b00000000000000001001010000100110 -
#98
0*
#99
1#
1*
b00000000000000001001010100101110 -
#100
0*
#101
0#
1*
b00000000000000001001010000100110 -
#102
0*
#103
1#
1*
b00000000000000001001010100101110 -
#104
0*
#105
0#
1*
b00000000000000001001010000100110 -
#106
0*
#107
1#
1*
b00000000000000001001010100101110 -
#108
0*
#109
0#
1*
b00000000000000001001010000100110 -
#110
0*
#111
1#
1*
b00000000000000001001010100101110 -
#112
0*
#113
0#
1*
b00000000000000001001010000100110 -
#114
0*
#115
1#
1*
b00000000000000001001010100101110 -
#116
0*
#117
0#
1*
b00000000000000001001010000100110 -
#118
0*
#119
1#
1*
b00000000000000001001010100101110 -
#120
0*
#121
0#
1*
b00000000000000001001010000100110 -
#122
0*
#123
1#
1*
b00000000000000001001010100101110 -
#124
0*
#125
0#
1*
b00000000000000001001010000100110 -
#126
0*
#127
1#
1*
b00000000000000001001010100101110 -
#128
0*
#129
0#
1*
b00000000000000001001010000100110 -
#130
0*
#131
1#
1*
b00000000000000001001010100101110 -
#132
0*
#133
0#
1*
b00000000000000001001010000100110 -
#134
0*
#135
1#
1*
b00000000000000001001010100101110 -
#136
0*
#137
0#
1*
b00000000000000001001010000100110 -
#138
0*
#139
1#
1*
b00000000000000001001010100101110 -
#140
0*
#141
0#
1*
b00000000000000001001010000100110 -
#142
0*
#143
1#
1*
b00000000000000001001010100101110 -
#144
0*
#145
0#
1*
b00000000000000001001010000100110 -
#146
0*
#147
1#
1*
b00000000000000001001010100101110 -
#148
0*
#149
0#
1*
b00000000000000001001010000100110 -
#150
0*
#151
1#
1*
b00000000000000001001010100101110 -
#152
0*
#153
0#
1*
b00000000000000001001010000100110 -
#154
0*
#155
1#
1*
b00000000000000001001010100101110 -
#156
0*
#157
0#
1*
b00000000000000001001010000100110 -
#158
0*
#159
1#
1*
b00000000000000001001010100101110 -
#160
0*
#161
0#
1*
b00000000000000001001010000100110 -
#162
0*
#163
1#
1*
b00000000000000001001010100101110 -
#164
0*
#165
0#
1*
b00000000000000001001010000100110 -
#166
0*
#167
1#
1*
b00000000000000001001010100101110 -
#168
0*
#169
0#
1*
b00000000000000001001010000100110 -
#170
0*
#171
1#
1*
b00000000000000001001010100101110 -
#172
0*
#173
0#
1*
b00000000000000001001010000100110 -
#174
0*
#175
1#
1*
b00000000000000001001010100101110 -
#176
0*
#177
0#
1*
b00000000000000001001010000100110 -
#178
0*
#179
1#
1*
b00000000000000001001010100101110 -
#180
0*
#181
0#
1*
b00000000000000001001010000100110 -
#182
0*
#183
1#
1*
b00000000000000001001010100101110 -
#184
0*
#185
0#
1*
b00000000000000001001010000100110 -
#186
0*
#187
1#
1*
b00000000000000001001010100101110 -
#188
0*
#189
0#
1*
b00000000000000001001010000100110 -
#190
0*
#191
1#
1*
b00000000000000001001010100101110 -
#192
0*
#193
0#
1*
b00000000000000001001010000100110 -
#194
0*
#195
1#
1*
b00000000000000001001010100101110 -
#196
0*
#197
0#
1*
b00000000000000001001010000100110 -
#198
0*
#199
1#
1*
b00000000000000001001010100101110 -
#200
0*
#201
0#
1*
b00000000000000001001010000100110 -
#202
0*
#203
1#
1*
b00000000000000001001010100101110 -
#204
0*
#205
0#
1*
b00000000000000001001010000100110 -
#206
0*
#207
1#
1*
b00000000000000001001010100101110 -
#208
0*
#209
0#
1*
b00000000000000001001010000100110 -
#210
0*
#211
1#
1*
b00000000000000001001010100101110 -
#212
0*
b00000000000000000000000000000000 ,
b00000000000000000000000000000000 .
b00000000000000000000000000000010 /
#213
0#
b0000000000000000 &
b00000000000000000000000000000000 '
b00000000000000000000000000000010 (
1*
b00000000000000000000000000000000 -
b00000000000000000000000000010100 /
