test_run_dir/Instruction_Aligner_Test/InstAligner.v
module InstAligner(
  input         clock,
  input         reset,
  input  [31:0] io_instIn,
  output [31:0] io_instOut,
  input  [31:0] io_pcIn,
  output [31:0] io_pcOut
);
`ifdef RANDOMIZE_REG_INIT
  reg [31:0] _RAND_0;
  reg [31:0] _RAND_1;
  reg [31:0] _RAND_2;
`endif // RANDOMIZE_REG_INIT
  reg  case1; // @[InstAligner.scala 16:24]
  reg  case2; // @[InstAligner.scala 17:24]
  reg [31:0] instReg; // @[InstAligner.scala 18:26]
  wire  _T = ~case1; // @[Conditional.scala 37:30]
  wire  _T_2 = io_instIn[1:0] != 2'h3; // @[InstAligner.scala 27:33]
  wire  _T_4 = io_instIn[17:16] != 2'h3; // @[InstAligner.scala 27:61]
  wire [31:0] _io_pcOut_T_1 = io_pcIn + 32'h2; // @[InstAligner.scala 31:37]
  wire [31:0] _GEN_0 = io_instIn[1:0] != 2'h3 & io_instIn[17:16] != 2'h3 ? {{16'd0}, io_instIn[15:0]} : instReg; // @[InstAligner.scala 27:69 InstAligner.scala 28:28 InstAligner.scala 20:16]
  wire [31:0] _GEN_1 = io_instIn[1:0] != 2'h3 & io_instIn[17:16] != 2'h3 ? io_instIn : instReg; // @[InstAligner.scala 27:69 InstAligner.scala 30:25 InstAligner.scala 18:26]
  wire [31:0] _GEN_2 = io_instIn[1:0] != 2'h3 & io_instIn[17:16] != 2'h3 ? _io_pcOut_T_1 : io_pcIn; // @[InstAligner.scala 27:69 InstAligner.scala 31:26 InstAligner.scala 19:14]
  wire  _GEN_3 = io_instIn[1:0] != 2'h3 & io_instIn[17:16] != 2'h3 | case1; // @[InstAligner.scala 27:69 InstAligner.scala 32:23 InstAligner.scala 16:24]
  wire  _GEN_4 = case1 ? 1'h0 : case1; // @[Conditional.scala 39:67 InstAligner.scala 36:19 InstAligner.scala 16:24]
  wire [31:0] _GEN_5 = case1 ? {{16'd0}, instReg[31:16]} : instReg; // @[Conditional.scala 39:67 InstAligner.scala 37:24 InstAligner.scala 20:16]
  wire [31:0] _GEN_6 = case1 ? _io_pcOut_T_1 : io_pcIn; // @[Conditional.scala 39:67 InstAligner.scala 39:22 InstAligner.scala 19:14]
  wire [31:0] _GEN_7 = _T ? _GEN_0 : _GEN_5; // @[Conditional.scala 40:58]
  wire [31:0] _GEN_8 = _T ? _GEN_1 : instReg; // @[Conditional.scala 40:58 InstAligner.scala 18:26]
  wire [31:0] _GEN_9 = _T ? _GEN_2 : _GEN_6; // @[Conditional.scala 40:58]
  wire  _GEN_10 = _T ? _GEN_3 : _GEN_4; // @[Conditional.scala 40:58]
  wire  _T_7 = ~case2; // @[Conditional.scala 37:30]
  wire  _T_11 = io_instIn[17:16] == 2'h3; // @[InstAligner.scala 45:61]
  wire [31:0] _GEN_11 = _T_2 & io_instIn[17:16] == 2'h3 ? {{16'd0}, io_instIn[15:0]} : _GEN_7; // @[InstAligner.scala 45:69 InstAligner.scala 46:28]
  wire [31:0] _GEN_13 = _T_2 & io_instIn[17:16] == 2'h3 ? _io_pcOut_T_1 : _GEN_9; // @[InstAligner.scala 45:69 InstAligner.scala 49:26]
  wire  _GEN_14 = _T_2 & io_instIn[17:16] == 2'h3 | case2; // @[InstAligner.scala 45:69 InstAligner.scala 50:23 InstAligner.scala 17:24]
  wire [31:0] _io_instOut_T_3 = {io_instIn[15:0],instReg[31:16]}; // @[Cat.scala 30:58]
  wire [31:0] _io_pcOut_T_7 = io_pcIn + 32'h4; // @[InstAligner.scala 56:33]
  wire [31:0] _GEN_15 = _T_11 ? io_instIn : _GEN_8; // @[InstAligner.scala 60:49 InstAligner.scala 61:25]
  wire [31:0] _GEN_20 = case2 ? _io_instOut_T_3 : _GEN_7; // @[Conditional.scala 39:67 InstAligner.scala 54:24]
  wire [31:0] _GEN_21 = case2 ? _io_pcOut_T_7 : _GEN_9; // @[Conditional.scala 39:67 InstAligner.scala 56:22]
  assign io_instOut = _T_7 ? _GEN_11 : _GEN_20; // @[Conditional.scala 40:58]
  assign io_pcOut = _T_7 ? _GEN_13 : _GEN_21; // @[Conditional.scala 40:58]
  always @(posedge clock) begin
    if (reset) begin // @[InstAligner.scala 16:24]
      case1 <= 1'h0; // @[InstAligner.scala 16:24]
    end else if (_T_7) begin // @[Conditional.scala 40:58]
      case1 <= _GEN_10;
    end else if (case2) begin // @[Conditional.scala 39:67]
      if (_T_4) begin // @[InstAligner.scala 57:44]
        case1 <= 1'h0; // @[InstAligner.scala 58:23]
      end else begin
        case1 <= _GEN_10;
      end
    end else begin
      case1 <= _GEN_10;
    end
    if (reset) begin // @[InstAligner.scala 17:24]
      case2 <= 1'h0; // @[InstAligner.scala 17:24]
    end else if (_T_7) begin // @[Conditional.scala 40:58]
      case2 <= _GEN_14;
    end else if (case2) begin // @[Conditional.scala 39:67]
      if (_T_4) begin // @[InstAligner.scala 57:44]
        case2 <= 1'h0; // @[InstAligner.scala 59:23]
      end else begin
        case2 <= _T_11;
      end
    end
    if (reset) begin // @[InstAligner.scala 18:26]
      instReg <= io_instIn; // @[InstAligner.scala 18:26]
    end else if (_T_7) begin // @[Conditional.scala 40:58]
      if (_T_2 & io_instIn[17:16] == 2'h3) begin // @[InstAligner.scala 45:69]
        instReg <= io_instIn; // @[InstAligner.scala 48:25]
      end else begin
        instReg <= _GEN_8;
      end
    end else if (case2) begin // @[Conditional.scala 39:67]
      if (_T_4) begin // @[InstAligner.scala 57:44]
        instReg <= _GEN_8;
      end else begin
        instReg <= _GEN_15;
      end
    end else begin
      instReg <= _GEN_8;
    end
  end
// Register and memory initialization
`ifdef RANDOMIZE_GARBAGE_ASSIGN
`define RANDOMIZE
`endif
`ifdef RANDOMIZE_INVALID_ASSIGN
`define RANDOMIZE
`endif
`ifdef RANDOMIZE_REG_INIT
`define RANDOMIZE
`endif
`ifdef RANDOMIZE_MEM_INIT
`define RANDOMIZE
`endif
`ifndef RANDOM
`define RANDOM $random
`endif
`ifdef RANDOMIZE_MEM_INIT
  integer initvar;
`endif
`ifndef SYNTHESIS
`ifdef FIRRTL_BEFORE_INITIAL
`FIRRTL_BEFORE_INITIAL
`endif
initial begin
  `ifdef RANDOMIZE
    `ifdef INIT_RANDOM
      `INIT_RANDOM
    `endif
    `ifndef VERILATOR
      `ifdef RANDOMIZE_DELAY
        #`RANDOMIZE_DELAY begin end
      `else
        #0.002 begin end
      `endif
    `endif
`ifdef RANDOMIZE_REG_INIT
  _RAND_0 = {1{`RANDOM}};
  case1 = _RAND_0[0:0];
  _RAND_1 = {1{`RANDOM}};
  case2 = _RAND_1[0:0];
  _RAND_2 = {1{`RANDOM}};
  instReg = _RAND_2[31:0];
`endif // RANDOMIZE_REG_INIT
  `endif // RANDOMIZE
end // initial
`ifdef FIRRTL_AFTER_INITIAL
`FIRRTL_AFTER_INITIAL
`endif
`endif // SYNTHESIS
endmodule

test_run_dir/Instruction_Aligner_Test/InstAligner.vcd
$version Generated by VerilatedVcd $end
$date Tue Jan 25 00:50:57 2022
 $end
$timescale   1ns $end

 $scope module TOP $end
  $var wire  1 & clock $end
  $var wire 32 ( io_instIn [31:0] $end
  $var wire 32 ) io_instOut [31:0] $end
  $var wire 32 * io_pcIn [31:0] $end
  $var wire 32 + io_pcOut [31:0] $end
  $var wire  1 ' reset $end
  $scope module InstAligner $end
   $var wire  1 # case1 $end
   $var wire  1 $ case2 $end
   $var wire  1 & clock $end
   $var wire 32 % instReg [31:0] $end
   $var wire 32 ( io_instIn [31:0] $end
   $var wire 32 ) io_instOut [31:0] $end
   $var wire 32 * io_pcIn [31:0] $end
   $var wire 32 + io_pcOut [31:0] $end
   $var wire  1 ' reset $end
  $upscope $end
 $upscope $end
$enddefinitions $end


#0
0#
0$
b00000000000000000000000000000000 %
0&
1'
b00000000000000000000000000000000 (
b00000000000000000000000000000000 )
b00000000000000000000000000000000 *
b00000000000000000000000000000010 +
#1
1&
#2
0&
0'
b00000100001100111001010000100110 (
b00000000000000001001010000100110 )
b00000000000000000000000000001100 *
b00000000000000000000000000001110 +
#3
1$
b00000100001100111001010000100110 %
1&
b10010100001001100000010000110011 )
b00000000000000000000000000010000 +
#4
0&
b10010101001011100000000010010100 (
b00000000100101000000010000110011 )
b00000000000000000000000000010000 *
b00000000000000000000000000010100 +
#5
0$
b10010101001011100000000010010100 %
1&
b00000000000000000000000010010100 )
b00000000000000000000000000010010 +
#6
0&
b00000000100101000000010000110011 (
b10010101001011100000000010010100 )
b00000000000000000000000000010010 *
#7
1&
#8
0&
#9
1&
#10
0&
#11
1&
#12
0&
#13
1&
#14
0&
#15
1&
#16
0&
#17
1&
#18
0&
#19
1&
#20
0&
#21
1&
#22
0&
#23
1&
#24
0&
#25
1&
#26
0&
#27
1&
#28
0&
#29
1&
#30
0&
#31
1&
#32
0&
#33
1&
#34
0&
#35
1&
#36
0&
#37
1&
#38
0&
#39
1&
#40
0&
#41
1&
#42
0&
#43
1&
#44
0&
#45
1&
#46
0&
#47
1&
#48
0&
#49
1&
#50
0&
#51
1&
#52
0&
#53
1&
#54
0&
#55
1&
#56
0&
#57
1&
#58
0&
#59
1&
#60
0&
#61
1&
#62
0&
#63
1&
#64
0&
#65
1&
#66
0&
#67
1&
#68
0&
#69
1&
#70
0&
#71
1&
#72
0&
#73
1&
#74
0&
#75
1&
#76
0&
#77
1&
#78
0&
#79
1&
#80
0&
#81
1&
#82
0&
#83
1&
#84
0&
#85
1&
#86
0&
#87
1&
#88
0&
#89
1&
#90
0&
#91
1&
#92
0&
#93
1&
#94
0&
#95
1&
#96
0&
#97
1&
#98
0&
#99
1&
#100
0&
#101
1&
#102
0&
#103
1&
#104
0&
#105
1&
#106
0&
#107
1&
#108
0&
#109
1&
#110
0&
#111
1&
#112
0&
#113
1&
#114
0&
#115
1&
#116
0&
#117
1&
#118
0&
#119
1&
#120
0&
#121
1&
#122
0&
#123
1&
#124
0&
#125
1&
#126
0&
#127
1&
#128
0&
#129
1&
#130
0&
#131
1&
#132
0&
#133
1&
#134
0&
#135
1&
#136
0&
#137
1&
#138
0&
#139
1&
#140
0&
#141
1&
#142
0&
#143
1&
#144
0&
#145
1&
#146
0&
#147
1&
#148
0&
#149
1&
#150
0&
#151
1&
#152
0&
#153
1&
#154
0&
#155
1&
#156
0&
#157
1&
#158
0&
#159
1&
#160
0&
#161
1&
#162
0&
#163
1&
#164
0&
#165
1&
#166
0&
#167
1&
#168
0&
#169
1&
#170
0&
#171
1&
#172
0&
#173
1&
#174
0&
#175
1&
#176
0&
#177
1&
#178
0&
#179
1&
#180
0&
#181
1&
#182
0&
#183
1&
#184
0&
#185
1&
#186
0&
#187
1&
#188
0&
#189
1&
#190
0&
#191
1&
#192
0&
#193
1&
#194
0&
#195
1&
#196
0&
#197
1&
#198
0&
#199
1&
#200
0&
#201
1&
#202
0&
#203
1&
#204
0&
#205
1&
#206
0&
b00000000000000000000000000000000 (
b00000000000000000000000000000000 )
b00000000000000000000000000000000 *
b00000000000000000000000000000010 +
#207
1#
b00000000000000000000000000000000 %
1&
